<annotation>
	<folder>images</folder>
	<filename>calc-130.jpeg</filename>
	<path>/Users/frankli/ScienceFair/AutomaticProctor/object_detection/workspace/training_demo/images/calc-130.jpeg</path>
	<source>
		<database>Unknown</database>
	</source>
	<size>
		<width>1000</width>
		<height>1333</height>
		<depth>3</depth>
	</size>
	<segmented>0</segmented>
	<object>
		<name>Calculator</name>
		<pose>Unspecified</pose>
		<truncated>0</truncated>
		<difficult>0</difficult>
		<bndbox>
			<xmin>285</xmin>
			<ymin>718</ymin>
			<xmax>671</xmax>
			<ymax>1016</ymax>
		</bndbox>
	</object>
</annotation>
